MANIFEST.in
README
requirements.txt
setup.py
ajenti.plugin.network.egg-info/PKG-INFO
ajenti.plugin.network.egg-info/SOURCES.txt
ajenti.plugin.network.egg-info/dependency_links.txt
ajenti.plugin.network.egg-info/requires.txt
ajenti.plugin.network.egg-info/top_level.txt
ajenti_plugin_network/README.md
ajenti_plugin_network/__init__.py
ajenti_plugin_network/api.py
ajenti_plugin_network/aug.py
ajenti_plugin_network/bower.json
ajenti_plugin_network/main.py
ajenti_plugin_network/plugin.yml
ajenti_plugin_network/requirements.txt
ajenti_plugin_network/views.py
ajenti_plugin_network/locale/app.pot
ajenti_plugin_network/locale/af/LC_MESSAGES/app.js
ajenti_plugin_network/locale/af/LC_MESSAGES/app.po
ajenti_plugin_network/locale/af/LC_MESSAGES/app.po~
ajenti_plugin_network/locale/ar/LC_MESSAGES/app.js
ajenti_plugin_network/locale/ar/LC_MESSAGES/app.po
ajenti_plugin_network/locale/ar/LC_MESSAGES/app.po~
ajenti_plugin_network/locale/be/LC_MESSAGES/app.js
ajenti_plugin_network/locale/be/LC_MESSAGES/app.po
ajenti_plugin_network/locale/be/LC_MESSAGES/app.po~
ajenti_plugin_network/locale/bg/LC_MESSAGES/app.js
ajenti_plugin_network/locale/bg/LC_MESSAGES/app.po
ajenti_plugin_network/locale/bg/LC_MESSAGES/app.po~
ajenti_plugin_network/locale/bn/LC_MESSAGES/app.js
ajenti_plugin_network/locale/bn/LC_MESSAGES/app.po
ajenti_plugin_network/locale/bn/LC_MESSAGES/app.po~
ajenti_plugin_network/locale/bs/LC_MESSAGES/app.js
ajenti_plugin_network/locale/bs/LC_MESSAGES/app.po
ajenti_plugin_network/locale/ca/LC_MESSAGES/app.js
ajenti_plugin_network/locale/ca/LC_MESSAGES/app.po
ajenti_plugin_network/locale/ca/LC_MESSAGES/app.po~
ajenti_plugin_network/locale/cs/LC_MESSAGES/app.js
ajenti_plugin_network/locale/cs/LC_MESSAGES/app.po
ajenti_plugin_network/locale/cs/LC_MESSAGES/app.po~
ajenti_plugin_network/locale/da/LC_MESSAGES/app.js
ajenti_plugin_network/locale/da/LC_MESSAGES/app.po
ajenti_plugin_network/locale/da/LC_MESSAGES/app.po~
ajenti_plugin_network/locale/de/LC_MESSAGES/app.js
ajenti_plugin_network/locale/de/LC_MESSAGES/app.po
ajenti_plugin_network/locale/de/LC_MESSAGES/app.po~
ajenti_plugin_network/locale/el/LC_MESSAGES/app.js
ajenti_plugin_network/locale/el/LC_MESSAGES/app.po
