Metadata-Version: 1.2
Name: ajenti.plugin.network
Version: 0.29
Summary: Network
Home-page: https://ajenti.org
Author: Ajenti project
Author-email: e@ajenti.org
License: UNKNOWN
Platform: UNKNOWN
Requires-Python: >=3
